ocifacts/__init__.py
ocifacts/bin/imgpkg
ocifacts-0.0.1.dist-info/LICENSE
ocifacts-0.0.1.dist-info/METADATA
ocifacts-0.0.1.dist-info/WHEEL
ocifacts-0.0.1.dist-info/top_level.txt
ocifacts-0.0.1.dist-info/RECORD
