Metadata-Version: 2.1
Name: ocifacts
Version: 0.0.1
Summary: Artifact storage using OCI registries
Home-page: https://github.com/old-ocean-creature/ocifacts
Maintainer: Sole Ahab
Project-URL: Documentation, https://github.com/old-ocean-creature/ocifacts
Project-URL: Code, https://github.com/old-ocean-creature/ocifacts
Project-URL: Issue tracker, https://github.com/old-ocean-creature/ocifacts/issues
Requires-Python: >=3.6
License-File: LICENSE
